flexihash/__init__.py
Flexihash-1.5.1.dist-info/LICENSE.txt
Flexihash-1.5.1.dist-info/METADATA
Flexihash-1.5.1.dist-info/WHEEL
Flexihash-1.5.1.dist-info/top_level.txt
Flexihash-1.5.1.dist-info/RECORD
