Metadata-Version: 2.1
Name: Flexihash
Version: 1.5.1
Summary: Python port of PHP Flexihash
Home-page: http://github.com/shish/flexihash-py
Author: Shish
Author-email: webmaster@shishnet.org
License: UNKNOWN
Platform: UNKNOWN
